sh_ocr_client/__init__.py
sh_ocr_client/client.py
sh_ocr_client-0.1.1.dist-info/licenses/LICENSE
sh_ocr_client-0.1.1.dist-info/METADATA
sh_ocr_client-0.1.1.dist-info/WHEEL
sh_ocr_client-0.1.1.dist-info/top_level.txt
sh_ocr_client-0.1.1.dist-info/RECORD
