Metadata-Version: 2.4
Name: sh-ocr-client
Version: 0.1.1
Summary: A Python client library for OCR service
Author: shuaronhong
License: MIT
Project-URL: Homepage, https://github.com/shuaronhong/Pin_Hw09
Project-URL: Repository, https://github.com/shuaronhong/Pin_Hw09
Project-URL: Issues, https://github.com/shuaronhong/Pin_Hw09/issues
Keywords: ocr,image-processing,text-recognition
Classifier: Development Status :: 3 - Alpha
Classifier: Intended Audience :: Developers
Classifier: License :: OSI Approved :: MIT License
Classifier: Programming Language :: Python :: 3
Classifier: Programming Language :: Python :: 3.9
Classifier: Programming Language :: Python :: 3.10
Classifier: Programming Language :: Python :: 3.11
Classifier: Programming Language :: Python :: 3.12
Classifier: Topic :: Software Development :: Libraries :: Python Modules
Classifier: Topic :: Scientific/Engineering :: Image Recognition
Requires-Python: >=3.9
License-File: LICENSE
Requires-Dist: requests>=2.25.0
Dynamic: license-file
